{
  "map_id": "L1122475",
  "display_name": "Old Gombak Road (Selangor)",
  "coordinates": {
    "lat": 3.3264,
    "lng": 101.7622
  },
  "species_pool": {
    "reebul1": {
      "weight": 0.5546,
      "tier": "common"
    },
    "orbflo1": {
      "weight": 0.5462,
      "tier": "common"
    },
    "whitre1": {
      "weight": 0.4706,
      "tier": "common"
    },
    "blcbul2": {
      "weight": 0.4622,
      "tier": "common"
    },
    "sttbab1": {
      "weight": 0.4538,
      "tier": "common"
    },
    "spebul1": {
      "weight": 0.4118,
      "tier": "common"
    },
    "scbbul1": {
      "weight": 0.353,
      "tier": "common"
    },
    "verfly4": {
      "weight": 0.3445,
      "tier": "common"
    },
    "scamin1": {
      "weight": 0.3361,
      "tier": "common"
    },
    "ABFL": {
      "weight": 0.3361,
      "tier": "common"
    },
    "blhbul1": {
      "weight": 0.2857,
      "tier": "common"
    },
    "asfblu1": {
      "weight": 0.2857,
      "tier": "common"
    },
    "sirnee1": {
      "weight": 0.2689,
      "tier": "common"
    },
    "habbul1": {
      "weight": 0.2605,
      "tier": "common"
    },
    "sttbul3": {
      "weight": 0.2605,
      "tier": "common"
    },
    "gybspi2": {
      "weight": 0.2521,
      "tier": "common"
    },
    "buvbul1": {
      "weight": 0.2437,
      "tier": "uncommon"
    },
    "gybbul1": {
      "weight": 0.2353,
      "tier": "uncommon"
    },
    "bwfshr1": {
      "weight": 0.2269,
      "tier": "uncommon"
    },
    "humwhe1": {
      "weight": 0.2269,
      "tier": "uncommon"
    },
    "gowbar2": {
      "weight": 0.2185,
      "tier": "uncommon"
    },
    "houswi1": {
      "weight": 0.2101,
      "tier": "uncommon"
    },
    "buebar2": {
      "weight": 0.2101,
      "tier": "uncommon"
    },
    "bchpar1": {
      "weight": 0.2101,
      "tier": "uncommon"
    },
    "ARWA": {
      "weight": 0.1933,
      "tier": "uncommon"
    },
    "yebflo2": {
      "weight": 0.1933,
      "tier": "uncommon"
    },
    "pltswi1": {
      "weight": 0.1849,
      "tier": "uncommon"
    },
    "gyhcaf1": {
      "weight": 0.1849,
      "tier": "uncommon"
    },
    "rufpri1": {
      "weight": 0.1849,
      "tier": "uncommon"
    },
    "litspi1": {
      "weight": 0.1849,
      "tier": "uncommon"
    },
    "tigshr1": {
      "weight": 0.1765,
      "tier": "uncommon"
    },
    "emedov2": {
      "weight": 0.1681,
      "tier": "uncommon"
    },
    "whbyuh1": {
      "weight": 0.1681,
      "tier": "uncommon"
    },
    "larwoo1": {
      "weight": 0.1681,
      "tier": "uncommon"
    },
    "greior2": {
      "weight": 0.1681,
      "tier": "uncommon"
    },
    "leglea1": {
      "weight": 0.1681,
      "tier": "uncommon"
    },
    "GRAW": {
      "weight": 0.1597,
      "tier": "uncommon"
    },
    "gyrtre1": {
      "weight": 0.1513,
      "tier": "uncommon"
    },
    "bwfshr2": {
      "weight": 0.1513,
      "tier": "uncommon"
    },
    "punsun1": {
      "weight": 0.1513,
      "tier": "uncommon"
    },
    "baybro1": {
      "weight": 0.1429,
      "tier": "uncommon"
    },
    "crseag1": {
      "weight": 0.1345,
      "tier": "uncommon"
    },
    "crbflo1": {
      "weight": 0.1345,
      "tier": "uncommon"
    },
    "rafmal1": {
      "weight": 0.1261,
      "tier": "uncommon"
    },
    "rhihor1": {
      "weight": 0.1261,
      "tier": "uncommon"
    },
    "soobar2": {
      "weight": 0.1261,
      "tier": "uncommon"
    },
    "grtdro1": {
      "weight": 0.1261,
      "tier": "uncommon"
    },
    "vefnut1": {
      "weight": 0.1261,
      "tier": "uncommon"
    },
    "lescus1": {
      "weight": 0.1177,
      "tier": "uncommon"
    },
    "chbmal2": {
      "weight": 0.1176,
      "tier": "uncommon"
    },
    "labcro1": {
      "weight": 0.1176,
      "tier": "uncommon"
    },
    "cinbul1": {
      "weight": 0.1176,
      "tier": "uncommon"
    },
    "yevbul1": {
      "weight": 0.1176,
      "tier": "uncommon"
    },
    "eacwar1": {
      "weight": 0.1176,
      "tier": "uncommon"
    },
    "pabfly2": {
      "weight": 0.1176,
      "tier": "uncommon"
    },
    "bltfal1": {
      "weight": 0.1092,
      "tier": "uncommon"
    },
    "pacswa1": {
      "weight": 0.1092,
      "tier": "uncommon"
    },
    "spespi2": {
      "weight": 0.1092,
      "tier": "uncommon"
    },
    "asidrc3": {
      "weight": 0.1009,
      "tier": "uncommon"
    },
    "btbeat2": {
      "weight": 0.1008,
      "tier": "uncommon"
    },
    "ruttai1": {
      "weight": 0.1008,
      "tier": "uncommon"
    },
    "whvmyn": {
      "weight": 0.1008,
      "tier": "uncommon"
    },
    "comtai1": {
      "weight": 0.0924,
      "tier": "uncommon"
    },
    "rbbeat1": {
      "weight": 0.084,
      "tier": "uncommon"
    },
    "ochbul2": {
      "weight": 0.084,
      "tier": "uncommon"
    },
    "strbul1": {
      "weight": 0.084,
      "tier": "uncommon"
    },
    "lobspi1": {
      "weight": 0.084,
      "tier": "uncommon"
    },
    "wrehor1": {
      "weight": 0.0757,
      "tier": "uncommon"
    },
    "btbeat1": {
      "weight": 0.0757,
      "tier": "uncommon"
    },
    "crwwoo1": {
      "weight": 0.0756,
      "tier": "uncommon"
    },
    "greior1": {
      "weight": 0.0756,
      "tier": "uncommon"
    },
    "BARS": {
      "weight": 0.0756,
      "tier": "uncommon"
    },
    "whrmun": {
      "weight": 0.0756,
      "tier": "uncommon"
    },
    "scrtro1": {
      "weight": 0.0672,
      "tier": "uncommon"
    },
    "fiemin1": {
      "weight": 0.0672,
      "tier": "uncommon"
    },
    "blnmon1": {
      "weight": 0.0672,
      "tier": "uncommon"
    },
    "dantai1": {
      "weight": 0.0672,
      "tier": "uncommon"
    },
    "yebpri1": {
      "weight": 0.0672,
      "tier": "uncommon"
    },
    "yebwar1": {
      "weight": 0.0672,
      "tier": "uncommon"
    },
    "rucsun2": {
      "weight": 0.0672,
      "tier": "uncommon"
    },
    "plasun1": {
      "weight": 0.0672,
      "tier": "uncommon"
    },
    "orbwoo1": {
      "weight": 0.0589,
      "tier": "uncommon"
    },
    "placuc1": {
      "weight": 0.0588,
      "tier": "uncommon"
    },
    "y00839": {
      "weight": 0.0588,
      "tier": "uncommon"
    },
    "burwoo1": {
      "weight": 0.0588,
      "tier": "uncommon"
    },
    "banbro1": {
      "weight": 0.0588,
      "tier": "uncommon"
    },
    "datori1": {
      "weight": 0.0588,
      "tier": "uncommon"
    },
    "gytbab1": {
      "weight": 0.0588,
      "tier": "uncommon"
    },
    "MUFL": {
      "weight": 0.0588,
      "tier": "uncommon"
    },
    "yevflo1": {
      "weight": 0.0588,
      "tier": "uncommon"
    },
    "blbmal1": {
      "weight": 0.0504,
      "tier": "uncommon"
    },
    "brbnee1": {
      "weight": 0.0504,
      "tier": "uncommon"
    },
    "blyhae1": {
      "weight": 0.0504,
      "tier": "uncommon"
    },
    "gabwoo3": {
      "weight": 0.0504,
      "tier": "uncommon"
    },
    "olwbul1": {
      "weight": 0.0504,
      "tier": "uncommon"
    },
    "chnfor1": {
      "weight": 0.0504,
      "tier": "uncommon"
    },
    "SBMU": {
      "weight": 0.0504,
      "tier": "uncommon"
    },
    "whchor2": {
      "weight": 0.0421,
      "tier": "rare"
    },
    "korfly1": {
      "weight": 0.0421,
      "tier": "rare"
    },
    "ZEBD": {
      "weight": 0.042,
      "tier": "rare"
    },
    "orihob2": {
      "weight": 0.042,
      "tier": "rare"
    },
    "bankin1": {
      "weight": 0.042,
      "tier": "rare"
    },
    "retbar1": {
      "weight": 0.042,
      "tier": "rare"
    },
    "marwoo1": {
      "weight": 0.042,
      "tier": "rare"
    },
    "banwoo2": {
      "weight": 0.042,
      "tier": "rare"
    },
    "gobger1": {
      "weight": 0.042,
      "tier": "rare"
    },
    "gyhbab1": {
      "weight": 0.042,
      "tier": "rare"
    },
    "asgsta1": {
      "weight": 0.042,
      "tier": "rare"
    },
    "yeespi1": {
      "weight": 0.042,
      "tier": "rare"
    },
    "REJU": {
      "weight": 0.0336,
      "tier": "rare"
    },
    "SPDO": {
      "weight": 0.0336,
      "tier": "rare"
    },
    "grecou1": {
      "weight": 0.0336,
      "tier": "rare"
    },
    "grbmal1": {
      "weight": 0.0336,
      "tier": "rare"
    },
    "PASW": {
      "weight": 0.0336,
      "tier": "rare"
    },
    "blaeag1": {
      "weight": 0.0336,
      "tier": "rare"
    },
    "yecbar1": {
      "weight": 0.0336,
      "tier": "rare"
    },
    "rufpic1": {
      "weight": 0.0336,
      "tier": "rare"
    },
    "ruwphi2": {
      "weight": 0.0336,
      "tier": "rare"
    },
    "sultit1": {
      "weight": 0.0336,
      "tier": "rare"
    },
    "DSFL": {
      "weight": 0.0336,
      "tier": "rare"
    },
    "plaflo2": {
      "weight": 0.0336,
      "tier": "rare"
    },
    "pltsun2": {
      "weight": 0.0336,
      "tier": "rare"
    },
    "retsun3": {
      "weight": 0.0336,
      "tier": "rare"
    },
    "ETSP": {
      "weight": 0.0336,
      "tier": "rare"
    },
    "chbmal1": {
      "weight": 0.0252,
      "tier": "rare"
    },
    "babcuc2": {
      "weight": 0.0252,
      "tier": "rare"
    },
    "malhac1": {
      "weight": 0.0252,
      "tier": "rare"
    },
    "indcuc1": {
      "weight": 0.0252,
      "tier": "rare"
    },
    "aspswi1": {
      "weight": 0.0252,
      "tier": "rare"
    },
    "rubeag2": {
      "weight": 0.0252,
      "tier": "rare"
    },
    "rufwoo2": {
      "weight": 0.0252,
      "tier": "rare"
    },
    "bamwoo1": {
      "weight": 0.0252,
      "tier": "rare"
    },
    "grebro1": {
      "weight": 0.0252,
      "tier": "rare"
    },
    "sibbro3": {
      "weight": 0.0252,
      "tier": "rare"
    },
    "gycmin1": {
      "weight": 0.0252,
      "tier": "rare"
    },
    "brodro1": {
      "weight": 0.0252,
      "tier": "rare"
    },
    "amupaf1": {
      "weight": 0.0252,
      "tier": "rare"
    },
    "ashtai1": {
      "weight": 0.0252,
      "tier": "rare"
    },
    "crvbul1": {
      "weight": 0.0252,
      "tier": "rare"
    },
    "chbscb2": {
      "weight": 0.0252,
      "tier": "rare"
    },
    "abbbab1": {
      "weight": 0.0252,
      "tier": "rare"
    },
    "junmyn1": {
      "weight": 0.0252,
      "tier": "rare"
    },
    "sibthr1": {
      "weight": 0.0252,
      "tier": "rare"
    },
    "bnsfly1": {
      "weight": 0.0252,
      "tier": "rare"
    },
    "thbpig1": {
      "weight": 0.0169,
      "tier": "rare"
    },
    "rebmal2": {
      "weight": 0.0169,
      "tier": "rare"
    },
    "BROS": {
      "weight": 0.0169,
      "tier": "rare"
    },
    "brucuc2": {
      "weight": 0.0168,
      "tier": "rare"
    },
    "y00731": {
      "weight": 0.0168,
      "tier": "rare"
    },
    "buchor1": {
      "weight": 0.0168,
      "tier": "rare"
    },
    "whtkin2": {
      "weight": 0.0168,
      "tier": "rare"
    },
    "bunwoo1": {
      "weight": 0.0168,
      "tier": "rare"
    },
    "barbro1": {
      "weight": 0.0168,
      "tier": "rare"
    },
    "ashmin1": {
      "weight": 0.0168,
      "tier": "rare"
    },
    "crbdro1": {
      "weight": 0.0168,
      "tier": "rare"
    },
    "rubswa1": {
      "weight": 0.0168,
      "tier": "rare"
    },
    "swiwhe1": {
      "weight": 0.0168,
      "tier": "rare"
    },
    "fbtbab1": {
      "weight": 0.0168,
      "tier": "rare"
    },
    "chwbab1": {
      "weight": 0.0168,
      "tier": "rare"
    },
    "shtbab1": {
      "weight": 0.0168,
      "tier": "rare"
    },
    "horbab2": {
      "weight": 0.0168,
      "tier": "rare"
    },
    "COMY": {
      "weight": 0.0168,
      "tier": "rare"
    },
    "orhthr1": {
      "weight": 0.0168,
      "tier": "rare"
    },
    "fibflo1": {
      "weight": 0.0168,
      "tier": "rare"
    },
    "whhmun1": {
      "weight": 0.0168,
      "tier": "rare"
    },
    "comior1": {
      "weight": 0.0085,
      "tier": "vagrant"
    },
    "rucfly1": {
      "weight": 0.0085,
      "tier": "vagrant"
    },
    "ROPI": {
      "weight": 0.0084,
      "tier": "vagrant"
    },
    "ligpig1": {
      "weight": 0.0084,
      "tier": "vagrant"
    },
    "lagpig1": {
      "weight": 0.0084,
      "tier": "vagrant"
    },
    "gripig1": {
      "weight": 0.0084,
      "tier": "vagrant"
    },
    "lescou1": {
      "weight": 0.0084,
      "tier": "vagrant"
    },
    "asikoe2": {
      "weight": 0.0084,
      "tier": "vagrant"
    },
    "libcuc1": {
      "weight": 0.0084,
      "tier": "vagrant"
    },
    "blnswi1": {
      "weight": 0.0084,
      "tier": "vagrant"
    },
    "walhae1": {
      "weight": 0.0084,
      "tier": "vagrant"
    },
    "cregos1": {
      "weight": 0.0084,
      "tier": "vagrant"
    },
    "japspa1": {
      "weight": 0.0084,
      "tier": "vagrant"
    },
    "CHIS": {
      "weight": 0.0084,
      "tier": "vagrant"
    },
    "brakit1": {
      "weight": 0.0084,
      "tier": "vagrant"
    },
    "rentro1": {
      "weight": 0.0084,
      "tier": "vagrant"
    },
    "diatro1": {
      "weight": 0.0084,
      "tier": "vagrant"
    },
    "grehor1": {
      "weight": 0.0084,
      "tier": "vagrant"
    },
    "colkin1": {
      "weight": 0.0084,
      "tier": "vagrant"
    },
    "ruckin1": {
      "weight": 0.0084,
      "tier": "vagrant"
    },
    "dollar1": {
      "weight": 0.0084,
      "tier": "vagrant"
    },
    "linbar1": {
      "weight": 0.0084,
      "tier": "vagrant"
    },
    "gycwoo1": {
      "weight": 0.0084,
      "tier": "vagrant"
    },
    "baywoo1": {
      "weight": 0.0084,
      "tier": "vagrant"
    },
    "blrpar1": {
      "weight": 0.0084,
      "tier": "vagrant"
    },
    "lotpar2": {
      "weight": 0.0084,
      "tier": "vagrant"
    },
    "besbab1": {
      "weight": 0.0084,
      "tier": "vagrant"
    },
    "mabphi2": {
      "weight": 0.0084,
      "tier": "vagrant"
    },
    "ashdro1": {
      "weight": 0.0084,
      "tier": "vagrant"
    },
    "blypaf1": {
      "weight": 0.0084,
      "tier": "vagrant"
    },
    "houcro1": {
      "weight": 0.0084,
      "tier": "vagrant"
    },
    "slbcro2": {
      "weight": 0.0084,
      "tier": "vagrant"
    },
    "pubbul1": {
      "weight": 0.0084,
      "tier": "vagrant"
    },
    "YBWA": {
      "weight": 0.0084,
      "tier": "vagrant"
    },
    "rufbab10": {
      "weight": 0.0084,
      "tier": "vagrant"
    },
    "rucbab2": {
      "weight": 0.0084,
      "tier": "vagrant"
    },
    "bkcbab1": {
      "weight": 0.0084,
      "tier": "vagrant"
    },
    "ferbab1": {
      "weight": 0.0084,
      "tier": "vagrant"
    },
    "broful1": {
      "weight": 0.0084,
      "tier": "vagrant"
    },
    "bawfly2": {
      "weight": 0.0084,
      "tier": "vagrant"
    },
    "hibfly1": {
      "weight": 0.0084,
      "tier": "vagrant"
    },
    "mabfly1": {
      "weight": 0.0084,
      "tier": "vagrant"
    },
    "narfly1": {
      "weight": 0.0084,
      "tier": "vagrant"
    },
    "thbflo1": {
      "weight": 0.0084,
      "tier": "vagrant"
    },
    "scbflo1": {
      "weight": 0.0084,
      "tier": "vagrant"
    },
    "olbsun4": {
      "weight": 0.0084,
      "tier": "vagrant"
    },
    "eacsun1": {
      "weight": 0.0084,
      "tier": "vagrant"
    },
    "goflea1": {
      "weight": 0.0084,
      "tier": "vagrant"
    },
    "baywea1": {
      "weight": 0.0084,
      "tier": "vagrant"
    },
    "viocuc1": {
      "weight": 0.0,
      "tier": "vagrant"
    },
    "whbwat1": {
      "weight": 0.0,
      "tier": "vagrant"
    },
    "bncwoo2": {
      "weight": 0.0,
      "tier": "vagrant"
    },
    "blnori1": {
      "weight": 0.0,
      "tier": "vagrant"
    },
    "spofan1": {
      "weight": 0.0,
      "tier": "vagrant"
    },
    "crejay1": {
      "weight": 0.0,
      "tier": "vagrant"
    },
    "tibfly4": {
      "weight": 0.0,
      "tier": "vagrant"
    },
    "forwag1": {
      "weight": 0.0,
      "tier": "vagrant"
    },
    "oripip1": {
      "weight": 0.0,
      "tier": "vagrant"
    }
  }
}