{
  "map_id": "L1344796",
  "display_name": "Oxford Island NR and Lough Neagh Discovery Centre",
  "coordinates": {
    "lat": 54.49578,
    "lng": -6.38335
  },
  "species_pool": {
    "MUSW": {
      "weight": 0.8788,
      "tier": "abundant"
    },
    "MALL": {
      "weight": 0.8737,
      "tier": "abundant"
    },
    "EUCO": {
      "weight": 0.8182,
      "tier": "abundant"
    },
    "grcgre1": {
      "weight": 0.8131,
      "tier": "abundant"
    },
    "TUDU": {
      "weight": 0.798,
      "tier": "abundant"
    },
    "BHGU": {
      "weight": 0.7879,
      "tier": "abundant"
    },
    "EURO": {
      "weight": 0.7677,
      "tier": "abundant"
    },
    "CCHA": {
      "weight": 0.7475,
      "tier": "common"
    },
    "CWPI": {
      "weight": 0.697,
      "tier": "common"
    },
    "blutit": {
      "weight": 0.6717,
      "tier": "common"
    },
    "litgre1": {
      "weight": 0.6667,
      "tier": "common"
    },
    "EUBB": {
      "weight": 0.6667,
      "tier": "common"
    },
    "eurmag1": {
      "weight": 0.6616,
      "tier": "common"
    },
    "gretit1": {
      "weight": 0.6515,
      "tier": "common"
    },
    "GRCO": {
      "weight": 0.6414,
      "tier": "common"
    },
    "HCRW": {
      "weight": 0.6061,
      "tier": "common"
    },
    "commoo3": {
      "weight": 0.5859,
      "tier": "common"
    },
    "winwre4": {
      "weight": 0.5758,
      "tier": "common"
    },
    "COMP": {
      "weight": 0.5556,
      "tier": "common"
    },
    "GRAH": {
      "weight": 0.5505,
      "tier": "common"
    },
    "WHWA": {
      "weight": 0.5152,
      "tier": "common"
    },
    "GADW": {
      "weight": 0.4899,
      "tier": "common"
    },
    "BARS": {
      "weight": 0.4394,
      "tier": "common"
    },
    "SOTH": {
      "weight": 0.4394,
      "tier": "common"
    },
    "dunnoc1": {
      "weight": 0.4243,
      "tier": "common"
    },
    "WEHM": {
      "weight": 0.399,
      "tier": "common"
    },
    "goldcr1": {
      "weight": 0.399,
      "tier": "common"
    },
    "LBBG": {
      "weight": 0.3889,
      "tier": "common"
    },
    "EUST": {
      "weight": 0.3586,
      "tier": "common"
    },
    "eurjay1": {
      "weight": 0.3334,
      "tier": "common"
    },
    "EUBC": {
      "weight": 0.3283,
      "tier": "common"
    },
    "coatit2": {
      "weight": 0.3232,
      "tier": "common"
    },
    "WILW": {
      "weight": 0.3232,
      "tier": "common"
    },
    "lottit1": {
      "weight": 0.3131,
      "tier": "common"
    },
    "HOSP": {
      "weight": 0.303,
      "tier": "common"
    },
    "EHGU": {
      "weight": 0.2677,
      "tier": "common"
    },
    "NOLA": {
      "weight": 0.2526,
      "tier": "common"
    },
    "EGOL": {
      "weight": 0.2526,
      "tier": "common"
    },
    "EUJA": {
      "weight": 0.2374,
      "tier": "uncommon"
    },
    "COTE": {
      "weight": 0.2222,
      "tier": "uncommon"
    },
    "COSW": {
      "weight": 0.2172,
      "tier": "uncommon"
    },
    "REBU": {
      "weight": 0.2172,
      "tier": "uncommon"
    },
    "MITH": {
      "weight": 0.2071,
      "tier": "uncommon"
    },
    "COGO": {
      "weight": 0.1718,
      "tier": "uncommon"
    },
    "WHOS": {
      "weight": 0.1717,
      "tier": "uncommon"
    },
    "SEWA": {
      "weight": 0.1717,
      "tier": "uncommon"
    },
    "EUBU": {
      "weight": 0.1717,
      "tier": "uncommon"
    },
    "GBBG": {
      "weight": 0.1667,
      "tier": "uncommon"
    },
    "combuz1": {
      "weight": 0.1667,
      "tier": "uncommon"
    },
    "ROOK": {
      "weight": 0.1616,
      "tier": "uncommon"
    },
    "CCHI": {
      "weight": 0.1616,
      "tier": "uncommon"
    },
    "eurtre1": {
      "weight": 0.1616,
      "tier": "uncommon"
    },
    "GSWO": {
      "weight": 0.1263,
      "tier": "uncommon"
    },
    "BANS": {
      "weight": 0.1162,
      "tier": "uncommon"
    },
    "GRSC": {
      "weight": 0.1113,
      "tier": "uncommon"
    },
    "GWTE": {
      "weight": 0.1111,
      "tier": "uncommon"
    },
    "COGU": {
      "weight": 0.1011,
      "tier": "uncommon"
    },
    "GRAW": {
      "weight": 0.0961,
      "tier": "uncommon"
    },
    "LIEG": {
      "weight": 0.0859,
      "tier": "uncommon"
    },
    "comkin1": {
      "weight": 0.0859,
      "tier": "uncommon"
    },
    "GRGO": {
      "weight": 0.0809,
      "tier": "uncommon"
    },
    "RNEP": {
      "weight": 0.0808,
      "tier": "uncommon"
    },
    "EUCD": {
      "weight": 0.0808,
      "tier": "uncommon"
    },
    "eurwar1": {
      "weight": 0.0708,
      "tier": "uncommon"
    },
    "ESPA": {
      "weight": 0.0657,
      "tier": "uncommon"
    },
    "ROPI": {
      "weight": 0.0606,
      "tier": "uncommon"
    },
    "EUSI": {
      "weight": 0.0606,
      "tier": "uncommon"
    },
    "REDW": {
      "weight": 0.0556,
      "tier": "uncommon"
    },
    "MEPI": {
      "weight": 0.0556,
      "tier": "uncommon"
    },
    "RBME": {
      "weight": 0.0404,
      "tier": "rare"
    },
    "NSHO": {
      "weight": 0.0354,
      "tier": "rare"
    },
    "EUGP": {
      "weight": 0.0354,
      "tier": "rare"
    },
    "RUDU": {
      "weight": 0.0305,
      "tier": "rare"
    },
    "EUCU": {
      "weight": 0.0305,
      "tier": "rare"
    },
    "ETSP": {
      "weight": 0.0304,
      "tier": "rare"
    },
    "COMS": {
      "weight": 0.0303,
      "tier": "rare"
    },
    "EUWI": {
      "weight": 0.0303,
      "tier": "rare"
    },
    "EUOY": {
      "weight": 0.0303,
      "tier": "rare"
    },
    "COSN": {
      "weight": 0.0303,
      "tier": "rare"
    },
    "CORA": {
      "weight": 0.0303,
      "tier": "rare"
    },
    "REDP": {
      "weight": 0.0303,
      "tier": "rare"
    },
    "watrai1": {
      "weight": 0.0253,
      "tier": "rare"
    },
    "EUKE": {
      "weight": 0.0253,
      "tier": "rare"
    },
    "EUSK": {
      "weight": 0.0253,
      "tier": "rare"
    },
    "FIEL": {
      "weight": 0.0253,
      "tier": "rare"
    },
    "RNDU": {
      "weight": 0.0203,
      "tier": "rare"
    },
    "LESC": {
      "weight": 0.0203,
      "tier": "rare"
    },
    "BLTG": {
      "weight": 0.0203,
      "tier": "rare"
    },
    "GREG": {
      "weight": 0.0203,
      "tier": "rare"
    },
    "TUSW": {
      "weight": 0.0202,
      "tier": "rare"
    },
    "SMEW": {
      "weight": 0.0202,
      "tier": "rare"
    },
    "COME": {
      "weight": 0.0202,
      "tier": "rare"
    },
    "COSA": {
      "weight": 0.0202,
      "tier": "rare"
    },
    "CREH": {
      "weight": 0.0202,
      "tier": "rare"
    },
    "stodov1": {
      "weight": 0.0152,
      "tier": "rare"
    },
    "DUNL": {
      "weight": 0.0152,
      "tier": "rare"
    },
    "BLTE": {
      "weight": 0.0152,
      "tier": "rare"
    },
    "eursha1": {
      "weight": 0.0152,
      "tier": "rare"
    },
    "CANG": {
      "weight": 0.0101,
      "tier": "rare"
    },
    "EUWH": {
      "weight": 0.0101,
      "tier": "rare"
    },
    "ARTE": {
      "weight": 0.0101,
      "tier": "rare"
    },
    "WTEA": {
      "weight": 0.0101,
      "tier": "rare"
    },
    "SPFL": {
      "weight": 0.0101,
      "tier": "rare"
    },
    "BRAM": {
      "weight": 0.0101,
      "tier": "rare"
    },
    "eurgre1": {
      "weight": 0.0101,
      "tier": "rare"
    },
    "blkswa": {
      "weight": 0.0051,
      "tier": "vagrant"
    },
    "recpoc": {
      "weight": 0.0051,
      "tier": "vagrant"
    },
    "COEI": {
      "weight": 0.0051,
      "tier": "vagrant"
    },
    "COCU": {
      "weight": 0.0051,
      "tier": "vagrant"
    },
    "CRPL": {
      "weight": 0.0051,
      "tier": "vagrant"
    },
    "COMG": {
      "weight": 0.0051,
      "tier": "vagrant"
    },
    "RUTU": {
      "weight": 0.0051,
      "tier": "vagrant"
    },
    "RUFF": {
      "weight": 0.0051,
      "tier": "vagrant"
    },
    "GRSK": {
      "weight": 0.0051,
      "tier": "vagrant"
    },
    "LIGU": {
      "weight": 0.0051,
      "tier": "vagrant"
    },
    "SATE": {
      "weight": 0.0051,
      "tier": "vagrant"
    },
    "COLO": {
      "weight": 0.0051,
      "tier": "vagrant"
    },
    "norhar1": {
      "weight": 0.0051,
      "tier": "vagrant"
    },
    "cogwar1": {
      "weight": 0.0051,
      "tier": "vagrant"
    },
    "garwar1": {
      "weight": 0.0051,
      "tier": "vagrant"
    },
    "eaywag1": {
      "weight": 0.0051,
      "tier": "vagrant"
    },
    "eurlin1": {
      "weight": 0.0051,
      "tier": "vagrant"
    },
    "GLIB": {
      "weight": 0.0001,
      "tier": "vagrant"
    },
    "OSPR": {
      "weight": 0.0001,
      "tier": "vagrant"
    },
    "BARG": {
      "weight": 0.0,
      "tier": "vagrant"
    },
    "NOPI": {
      "weight": 0.0,
      "tier": "vagrant"
    },
    "JASN": {
      "weight": 0.0,
      "tier": "vagrant"
    },
    "REKN": {
      "weight": 0.0,
      "tier": "vagrant"
    },
    "ROST": {
      "weight": 0.0,
      "tier": "vagrant"
    },
    "EAGR": {
      "weight": 0.0,
      "tier": "vagrant"
    },
    "stonec4": {
      "weight": 0.0,
      "tier": "vagrant"
    },
    "NOWH": {
      "weight": 0.0,
      "tier": "vagrant"
    }
  }
}