{
  "map_id": "L22537740",
  "display_name": "Camiguin Airport",
  "coordinates": {
    "lat": 9.25101,
    "lng": 124.704911
  },
  "species_pool": {
    "asgsta1": {
      "weight": 0.8667,
      "tier": "abundant"
    },
    "whbwoo4": {
      "weight": 0.8,
      "tier": "abundant"
    },
    "ETSP": {
      "weight": 0.8,
      "tier": "abundant"
    },
    "pacswa1": {
      "weight": 0.4667,
      "tier": "common"
    },
    "yevbul1": {
      "weight": 0.4667,
      "tier": "common"
    },
    "ROPI": {
      "weight": 0.3333,
      "tier": "common"
    },
    "SPDO": {
      "weight": 0.3333,
      "tier": "common"
    },
    "labcro15": {
      "weight": 0.3333,
      "tier": "common"
    },
    "piebus1": {
      "weight": 0.3333,
      "tier": "common"
    },
    "olbsun31": {
      "weight": 0.3333,
      "tier": "common"
    },
    "oripip1": {
      "weight": 0.3333,
      "tier": "common"
    },
    "BROS": {
      "weight": 0.2667,
      "tier": "common"
    },
    "BARS": {
      "weight": 0.2667,
      "tier": "common"
    },
    "CHMU": {
      "weight": 0.2003,
      "tier": "uncommon"
    },
    "ZEBD": {
      "weight": 0.2,
      "tier": "uncommon"
    },
    "brakit1": {
      "weight": 0.2,
      "tier": "uncommon"
    },
    "colkin1": {
      "weight": 0.1336,
      "tier": "uncommon"
    },
    "ridswi1": {
      "weight": 0.1333,
      "tier": "uncommon"
    },
    "palswi2": {
      "weight": 0.1333,
      "tier": "uncommon"
    },
    "aspswi1": {
      "weight": 0.1333,
      "tier": "uncommon"
    },
    "pietri1": {
      "weight": 0.1333,
      "tier": "uncommon"
    },
    "phipif1": {
      "weight": 0.1333,
      "tier": "uncommon"
    },
    "whbmun1": {
      "weight": 0.1333,
      "tier": "uncommon"
    },
    "recdov1": {
      "weight": 0.067,
      "tier": "uncommon"
    },
    "whedov1": {
      "weight": 0.0667,
      "tier": "uncommon"
    },
    "pinpig3": {
      "weight": 0.0667,
      "tier": "uncommon"
    },
    "lescou1": {
      "weight": 0.0667,
      "tier": "uncommon"
    },
    "barrai1": {
      "weight": 0.0667,
      "tier": "uncommon"
    },
    "LIEG": {
      "weight": 0.0667,
      "tier": "uncommon"
    },
    "japher1": {
      "weight": 0.0667,
      "tier": "uncommon"
    },
    "EACE": {
      "weight": 0.0667,
      "tier": "uncommon"
    },
    "MEEG": {
      "weight": 0.0667,
      "tier": "uncommon"
    },
    "tawgra3": {
      "weight": 0.0667,
      "tier": "uncommon"
    },
    "yelbul4": {
      "weight": 0.0667,
      "tier": "uncommon"
    },
    "evweye1": {
      "weight": 0.0667,
      "tier": "uncommon"
    },
    "phimar1": {
      "weight": 0.0667,
      "tier": "uncommon"
    },
    "orbflo1": {
      "weight": 0.0667,
      "tier": "uncommon"
    },
    "GRAW": {
      "weight": 0.0667,
      "tier": "uncommon"
    }
  }
}