{
  "map_id": "L25285877",
  "display_name": "Польское кладбище (Old Catholic Cemetery)",
  "coordinates": {
    "lat": 54.7728718,
    "lng": 32.0552469
  },
  "species_pool": {
    "EUJA": {
      "weight": 0.9091,
      "tier": "abundant"
    },
    "gretit1": {
      "weight": 0.9091,
      "tier": "abundant"
    },
    "ROPI": {
      "weight": 0.8182,
      "tier": "abundant"
    },
    "HCRW": {
      "weight": 0.6667,
      "tier": "common"
    },
    "CCHA": {
      "weight": 0.5152,
      "tier": "common"
    },
    "EGOL": {
      "weight": 0.5152,
      "tier": "common"
    },
    "blutit": {
      "weight": 0.4848,
      "tier": "common"
    },
    "FIEL": {
      "weight": 0.4545,
      "tier": "common"
    },
    "COGU": {
      "weight": 0.4242,
      "tier": "common"
    },
    "EUST": {
      "weight": 0.3939,
      "tier": "common"
    },
    "ROOK": {
      "weight": 0.3333,
      "tier": "common"
    },
    "eurnut2": {
      "weight": 0.3333,
      "tier": "common"
    },
    "eurtre1": {
      "weight": 0.2727,
      "tier": "common"
    },
    "EUBU": {
      "weight": 0.2727,
      "tier": "common"
    },
    "COSW": {
      "weight": 0.2424,
      "tier": "uncommon"
    },
    "EUBB": {
      "weight": 0.2424,
      "tier": "uncommon"
    },
    "BHGU": {
      "weight": 0.2121,
      "tier": "uncommon"
    },
    "SPFL": {
      "weight": 0.2121,
      "tier": "uncommon"
    },
    "ICWA": {
      "weight": 0.1818,
      "tier": "uncommon"
    },
    "EUBC": {
      "weight": 0.1818,
      "tier": "uncommon"
    },
    "ETSP": {
      "weight": 0.1818,
      "tier": "uncommon"
    },
    "eurgre1": {
      "weight": 0.1818,
      "tier": "uncommon"
    },
    "EURO": {
      "weight": 0.1515,
      "tier": "uncommon"
    },
    "thrnig1": {
      "weight": 0.1515,
      "tier": "uncommon"
    },
    "eupfly1": {
      "weight": 0.1212,
      "tier": "uncommon"
    },
    "WHWA": {
      "weight": 0.1212,
      "tier": "uncommon"
    },
    "eurmag1": {
      "weight": 0.0909,
      "tier": "uncommon"
    },
    "eurser1": {
      "weight": 0.0909,
      "tier": "uncommon"
    },
    "CWPI": {
      "weight": 0.0606,
      "tier": "uncommon"
    },
    "GSWO": {
      "weight": 0.0606,
      "tier": "uncommon"
    },
    "WILW": {
      "weight": 0.0606,
      "tier": "uncommon"
    },
    "MALL": {
      "weight": 0.0303,
      "tier": "rare"
    },
    "miswoo1": {
      "weight": 0.0303,
      "tier": "rare"
    },
    "eugori2": {
      "weight": 0.0303,
      "tier": "rare"
    },
    "eurjay1": {
      "weight": 0.0303,
      "tier": "rare"
    },
    "BREW": {
      "weight": 0.0303,
      "tier": "rare"
    },
    "WOWA": {
      "weight": 0.0303,
      "tier": "rare"
    },
    "CCHI": {
      "weight": 0.0303,
      "tier": "rare"
    },
    "lottit1": {
      "weight": 0.0303,
      "tier": "rare"
    },
    "goldcr1": {
      "weight": 0.0303,
      "tier": "rare"
    },
    "SOTH": {
      "weight": 0.0303,
      "tier": "rare"
    },
    "blared1": {
      "weight": 0.0303,
      "tier": "rare"
    },
    "HAWF": {
      "weight": 0.0303,
      "tier": "rare"
    }
  }
}