{
  "map_id": "L26062664",
  "display_name": "Tasik Kenyir--Jalan Pengkalan Utama",
  "coordinates": {
    "lat": 5.1476433,
    "lng": 102.7671795
  },
  "species_pool": {
    "baybro1": {
      "weight": 0.6923,
      "tier": "common"
    },
    "whitre1": {
      "weight": 0.6538,
      "tier": "common"
    },
    "buvbul1": {
      "weight": 0.5385,
      "tier": "common"
    },
    "reebul1": {
      "weight": 0.5385,
      "tier": "common"
    },
    "dantai1": {
      "weight": 0.5,
      "tier": "common"
    },
    "asfblu1": {
      "weight": 0.5,
      "tier": "common"
    },
    "orbflo1": {
      "weight": 0.4615,
      "tier": "common"
    },
    "emedov2": {
      "weight": 0.4231,
      "tier": "common"
    },
    "sttbab1": {
      "weight": 0.4231,
      "tier": "common"
    },
    "rafmal1": {
      "weight": 0.3846,
      "tier": "common"
    },
    "rhihor1": {
      "weight": 0.3846,
      "tier": "common"
    },
    "buebar2": {
      "weight": 0.3846,
      "tier": "common"
    },
    "greior2": {
      "weight": 0.3846,
      "tier": "common"
    },
    "crvbul1": {
      "weight": 0.3846,
      "tier": "common"
    },
    "chnfor1": {
      "weight": 0.3846,
      "tier": "common"
    },
    "sirnee1": {
      "weight": 0.3462,
      "tier": "common"
    },
    "orphor1": {
      "weight": 0.3462,
      "tier": "common"
    },
    "retbar1": {
      "weight": 0.3462,
      "tier": "common"
    },
    "scamin1": {
      "weight": 0.3462,
      "tier": "common"
    },
    "finbul1": {
      "weight": 0.3462,
      "tier": "common"
    },
    "datori1": {
      "weight": 0.3077,
      "tier": "common"
    },
    "bwfshr2": {
      "weight": 0.3077,
      "tier": "common"
    },
    "habbul1": {
      "weight": 0.3077,
      "tier": "common"
    },
    "fbtbab1": {
      "weight": 0.3077,
      "tier": "common"
    },
    "chwbab1": {
      "weight": 0.3077,
      "tier": "common"
    },
    "punsun1": {
      "weight": 0.3077,
      "tier": "common"
    },
    "leglea1": {
      "weight": 0.3077,
      "tier": "common"
    },
    "whchor2": {
      "weight": 0.2692,
      "tier": "common"
    },
    "labcro1": {
      "weight": 0.2692,
      "tier": "common"
    },
    "rufpri1": {
      "weight": 0.2692,
      "tier": "common"
    },
    "pacswa1": {
      "weight": 0.2692,
      "tier": "common"
    },
    "blhbul1": {
      "weight": 0.2692,
      "tier": "common"
    },
    "spebul1": {
      "weight": 0.2692,
      "tier": "common"
    },
    "humwhe1": {
      "weight": 0.2692,
      "tier": "common"
    },
    "crbflo1": {
      "weight": 0.2692,
      "tier": "common"
    },
    "wrehor1": {
      "weight": 0.2308,
      "tier": "uncommon"
    },
    "gobger1": {
      "weight": 0.2308,
      "tier": "uncommon"
    },
    "bwfshr1": {
      "weight": 0.2308,
      "tier": "uncommon"
    },
    "gyhcaf1": {
      "weight": 0.2308,
      "tier": "uncommon"
    },
    "gybbul1": {
      "weight": 0.2308,
      "tier": "uncommon"
    },
    "grearg1": {
      "weight": 0.1923,
      "tier": "uncommon"
    },
    "chbmal2": {
      "weight": 0.1923,
      "tier": "uncommon"
    },
    "asidrc3": {
      "weight": 0.1923,
      "tier": "uncommon"
    },
    "buchor1": {
      "weight": 0.1923,
      "tier": "uncommon"
    },
    "bankin1": {
      "weight": 0.1923,
      "tier": "uncommon"
    },
    "crwwoo1": {
      "weight": 0.1923,
      "tier": "uncommon"
    },
    "banbro1": {
      "weight": 0.1923,
      "tier": "uncommon"
    },
    "larwoo1": {
      "weight": 0.1923,
      "tier": "uncommon"
    },
    "yevbul1": {
      "weight": 0.1923,
      "tier": "uncommon"
    },
    "yebflo2": {
      "weight": 0.1923,
      "tier": "uncommon"
    },
    "plasun1": {
      "weight": 0.1923,
      "tier": "uncommon"
    },
    "placuc1": {
      "weight": 0.1538,
      "tier": "uncommon"
    },
    "y00731": {
      "weight": 0.1538,
      "tier": "uncommon"
    },
    "crseag1": {
      "weight": 0.1538,
      "tier": "uncommon"
    },
    "whtkin2": {
      "weight": 0.1538,
      "tier": "uncommon"
    },
    "lescus1": {
      "weight": 0.1538,
      "tier": "uncommon"
    },
    "ashtai1": {
      "weight": 0.1538,
      "tier": "uncommon"
    },
    "moubab1": {
      "weight": 0.1538,
      "tier": "uncommon"
    },
    "litspi1": {
      "weight": 0.1538,
      "tier": "uncommon"
    },
    "viocuc1": {
      "weight": 0.1154,
      "tier": "uncommon"
    },
    "y00839": {
      "weight": 0.1154,
      "tier": "uncommon"
    },
    "scrtro1": {
      "weight": 0.1154,
      "tier": "uncommon"
    },
    "rbbeat1": {
      "weight": 0.1154,
      "tier": "uncommon"
    },
    "soobar2": {
      "weight": 0.1154,
      "tier": "uncommon"
    },
    "yecbar1": {
      "weight": 0.1154,
      "tier": "uncommon"
    },
    "chtwoo1": {
      "weight": 0.1154,
      "tier": "uncommon"
    },
    "bchpar1": {
      "weight": 0.1154,
      "tier": "uncommon"
    },
    "ruwphi2": {
      "weight": 0.1154,
      "tier": "uncommon"
    },
    "blnmon1": {
      "weight": 0.1154,
      "tier": "uncommon"
    },
    "sultit1": {
      "weight": 0.1154,
      "tier": "uncommon"
    },
    "chrbab1": {
      "weight": 0.1154,
      "tier": "uncommon"
    },
    "shtbab1": {
      "weight": 0.1154,
      "tier": "uncommon"
    },
    "pabfly2": {
      "weight": 0.1154,
      "tier": "uncommon"
    },
    "scbflo2": {
      "weight": 0.1154,
      "tier": "uncommon"
    },
    "yevflo1": {
      "weight": 0.1154,
      "tier": "uncommon"
    },
    "pltsun2": {
      "weight": 0.1154,
      "tier": "uncommon"
    },
    "wbseag1": {
      "weight": 0.0773,
      "tier": "uncommon"
    },
    "banwoo2": {
      "weight": 0.0773,
      "tier": "uncommon"
    },
    "ZEBD": {
      "weight": 0.0769,
      "tier": "uncommon"
    },
    "thbpig1": {
      "weight": 0.0769,
      "tier": "uncommon"
    },
    "rebmal2": {
      "weight": 0.0769,
      "tier": "uncommon"
    },
    "blbmal1": {
      "weight": 0.0769,
      "tier": "uncommon"
    },
    "gyrtre1": {
      "weight": 0.0769,
      "tier": "uncommon"
    },
    "blyhae1": {
      "weight": 0.0769,
      "tier": "uncommon"
    },
    "lefeag1": {
      "weight": 0.0769,
      "tier": "uncommon"
    },
    "resowl1": {
      "weight": 0.0769,
      "tier": "uncommon"
    },
    "rufpic1": {
      "weight": 0.0769,
      "tier": "uncommon"
    },
    "orbwoo1": {
      "weight": 0.0769,
      "tier": "uncommon"
    },
    "bunwoo1": {
      "weight": 0.0769,
      "tier": "uncommon"
    },
    "grebro1": {
      "weight": 0.0769,
      "tier": "uncommon"
    },
    "barbro1": {
      "weight": 0.0769,
      "tier": "uncommon"
    },
    "fiemin1": {
      "weight": 0.0769,
      "tier": "uncommon"
    },
    "whbyuh1": {
      "weight": 0.0769,
      "tier": "uncommon"
    },
    "comior1": {
      "weight": 0.0769,
      "tier": "uncommon"
    },
    "comtai1": {
      "weight": 0.0769,
      "tier": "uncommon"
    },
    "yebpri1": {
      "weight": 0.0769,
      "tier": "uncommon"
    },
    "ARWA": {
      "weight": 0.0769,
      "tier": "uncommon"
    },
    "whvmyn": {
      "weight": 0.0769,
      "tier": "uncommon"
    },
    "ABFL": {
      "weight": 0.0769,
      "tier": "uncommon"
    },
    "verfly4": {
      "weight": 0.0769,
      "tier": "uncommon"
    },
    "rucsun2": {
      "weight": 0.0769,
      "tier": "uncommon"
    },
    "lobspi1": {
      "weight": 0.0769,
      "tier": "uncommon"
    },
    "gybspi2": {
      "weight": 0.0769,
      "tier": "uncommon"
    },
    "ETSP": {
      "weight": 0.0769,
      "tier": "uncommon"
    },
    "GRAW": {
      "weight": 0.0769,
      "tier": "uncommon"
    },
    "REJU": {
      "weight": 0.0385,
      "tier": "rare"
    },
    "SPDO": {
      "weight": 0.0385,
      "tier": "rare"
    },
    "ligpig1": {
      "weight": 0.0385,
      "tier": "rare"
    },
    "pinpig3": {
      "weight": 0.0385,
      "tier": "rare"
    },
    "asikoe2": {
      "weight": 0.0385,
      "tier": "rare"
    },
    "libcuc1": {
      "weight": 0.0385,
      "tier": "rare"
    },
    "babcuc2": {
      "weight": 0.0385,
      "tier": "rare"
    },
    "indcuc1": {
      "weight": 0.0385,
      "tier": "rare"
    },
    "brbnee1": {
      "weight": 0.0385,
      "tier": "rare"
    },
    "pltswi1": {
      "weight": 0.0385,
      "tier": "rare"
    },
    "aspswi1": {
      "weight": 0.0385,
      "tier": "rare"
    },
    "rewlap1": {
      "weight": 0.0385,
      "tier": "rare"
    },
    "asiope1": {
      "weight": 0.0385,
      "tier": "rare"
    },
    "LIEG": {
      "weight": 0.0385,
      "tier": "rare"
    },
    "rubeag2": {
      "weight": 0.0385,
      "tier": "rare"
    },
    "bufowl2": {
      "weight": 0.0385,
      "tier": "rare"
    },
    "spwowl1": {
      "weight": 0.0385,
      "tier": "rare"
    },
    "grehor1": {
      "weight": 0.0385,
      "tier": "rare"
    },
    "btbeat2": {
      "weight": 0.0385,
      "tier": "rare"
    },
    "colkin1": {
      "weight": 0.0385,
      "tier": "rare"
    },
    "ruckin1": {
      "weight": 0.0385,
      "tier": "rare"
    },
    "copbar1": {
      "weight": 0.0385,
      "tier": "rare"
    },
    "linbar1": {
      "weight": 0.0385,
      "tier": "rare"
    },
    "burwoo1": {
      "weight": 0.0385,
      "tier": "rare"
    },
    "bltfal1": {
      "weight": 0.0385,
      "tier": "rare"
    },
    "blwpit1": {
      "weight": 0.0385,
      "tier": "rare"
    },
    "ashmin1": {
      "weight": 0.0385,
      "tier": "rare"
    },
    "pietri1": {
      "weight": 0.0385,
      "tier": "rare"
    },
    "blnori1": {
      "weight": 0.0385,
      "tier": "rare"
    },
    "greior1": {
      "weight": 0.0385,
      "tier": "rare"
    },
    "piefan1": {
      "weight": 0.0385,
      "tier": "rare"
    },
    "blkmag1": {
      "weight": 0.0385,
      "tier": "rare"
    },
    "ruttai1": {
      "weight": 0.0385,
      "tier": "rare"
    },
    "yebbul2": {
      "weight": 0.0385,
      "tier": "rare"
    },
    "olwbul1": {
      "weight": 0.0385,
      "tier": "rare"
    },
    "sttbul3": {
      "weight": 0.0385,
      "tier": "rare"
    },
    "eacwar1": {
      "weight": 0.0385,
      "tier": "rare"
    },
    "rufbab10": {
      "weight": 0.0385,
      "tier": "rare"
    },
    "broful1": {
      "weight": 0.0385,
      "tier": "rare"
    },
    "asgsta1": {
      "weight": 0.0385,
      "tier": "rare"
    },
    "COMY": {
      "weight": 0.0385,
      "tier": "rare"
    },
    "junmyn1": {
      "weight": 0.0385,
      "tier": "rare"
    },
    "DSFL": {
      "weight": 0.0385,
      "tier": "rare"
    },
    "tibfly4": {
      "weight": 0.0385,
      "tier": "rare"
    },
    "korfly1": {
      "weight": 0.0385,
      "tier": "rare"
    },
    "plaflo2": {
      "weight": 0.0385,
      "tier": "rare"
    },
    "SBMU": {
      "weight": 0.0385,
      "tier": "rare"
    },
    "whrmun": {
      "weight": 0.0385,
      "tier": "rare"
    },
    "whbmun1": {
      "weight": 0.0385,
      "tier": "rare"
    },
    "oripip1": {
      "weight": 0.0385,
      "tier": "rare"
    }
  }
}