{
  "map_id": "L405301",
  "display_name": "Westport pelagic--Offshore waters",
  "coordinates": {
    "lat": 46.9052455,
    "lng": -124.5355225
  },
  "species_pool": {
    "SOSH": {
      "weight": 0.9549,
      "tier": "abundant"
    },
    "COMU": {
      "weight": 0.9244,
      "tier": "abundant"
    },
    "RHAU": {
      "weight": 0.8939,
      "tier": "abundant"
    },
    "PFSH": {
      "weight": 0.8815,
      "tier": "abundant"
    },
    "BFAL": {
      "weight": 0.8014,
      "tier": "abundant"
    },
    "NOFU": {
      "weight": 0.7968,
      "tier": "abundant"
    },
    "CAGU": {
      "weight": 0.7788,
      "tier": "abundant"
    },
    "CAAU": {
      "weight": 0.7494,
      "tier": "common"
    },
    "FTSP": {
      "weight": 0.7325,
      "tier": "common"
    },
    "RNPH": {
      "weight": 0.6196,
      "tier": "common"
    },
    "SAGU": {
      "weight": 0.5982,
      "tier": "common"
    },
    "POJA": {
      "weight": 0.5892,
      "tier": "common"
    },
    "SPSK": {
      "weight": 0.4661,
      "tier": "common"
    },
    "BULS": {
      "weight": 0.421,
      "tier": "common"
    },
    "REPH": {
      "weight": 0.3815,
      "tier": "common"
    },
    "PAJA": {
      "weight": 0.3691,
      "tier": "common"
    },
    "STTS": {
      "weight": 0.3251,
      "tier": "common"
    },
    "TUPU": {
      "weight": 0.3115,
      "tier": "common"
    },
    "PALO": {
      "weight": 0.263,
      "tier": "common"
    },
    "AHGU": {
      "weight": 0.2596,
      "tier": "common"
    },
    "BRPE": {
      "weight": 0.2303,
      "tier": "uncommon"
    },
    "WEGU": {
      "weight": 0.2246,
      "tier": "uncommon"
    },
    "ARTE": {
      "weight": 0.2167,
      "tier": "uncommon"
    },
    "LTJA": {
      "weight": 0.2009,
      "tier": "uncommon"
    },
    "COLO": {
      "weight": 0.1998,
      "tier": "uncommon"
    },
    "GWGU": {
      "weight": 0.1896,
      "tier": "uncommon"
    },
    "BLKI": {
      "weight": 0.1841,
      "tier": "uncommon"
    },
    "BRAC": {
      "weight": 0.1795,
      "tier": "uncommon"
    },
    "FFSH": {
      "weight": 0.1727,
      "tier": "uncommon"
    },
    "PIGU": {
      "weight": 0.1682,
      "tier": "uncommon"
    },
    "LESP": {
      "weight": 0.1591,
      "tier": "uncommon"
    },
    "SUSC": {
      "weight": 0.1467,
      "tier": "uncommon"
    },
    "HEGU": {
      "weight": 0.1287,
      "tier": "uncommon"
    },
    "WWSC": {
      "weight": 0.1219,
      "tier": "uncommon"
    },
    "COTE": {
      "weight": 0.1129,
      "tier": "uncommon"
    },
    "PECO": {
      "weight": 0.0903,
      "tier": "uncommon"
    },
    "LAAL": {
      "weight": 0.0869,
      "tier": "uncommon"
    },
    "RTLO": {
      "weight": 0.0858,
      "tier": "uncommon"
    },
    "ANMU": {
      "weight": 0.0813,
      "tier": "uncommon"
    },
    "WEGR": {
      "weight": 0.0767,
      "tier": "uncommon"
    },
    "SBIG": {
      "weight": 0.0655,
      "tier": "uncommon"
    },
    "DCCO": {
      "weight": 0.061,
      "tier": "uncommon"
    },
    "NOPI": {
      "weight": 0.0587,
      "tier": "uncommon"
    },
    "BOGU": {
      "weight": 0.0542,
      "tier": "uncommon"
    },
    "GWTE": {
      "weight": 0.053,
      "tier": "uncommon"
    },
    "ICGU": {
      "weight": 0.0508,
      "tier": "uncommon"
    },
    "MASH": {
      "weight": 0.0463,
      "tier": "rare"
    },
    "MAMU": {
      "weight": 0.0453,
      "tier": "rare"
    },
    "SCMU": {
      "weight": 0.0418,
      "tier": "rare"
    },
    "CATE": {
      "weight": 0.0406,
      "tier": "rare"
    },
    "BRAN": {
      "weight": 0.0305,
      "tier": "rare"
    },
    "PAAU": {
      "weight": 0.0293,
      "tier": "rare"
    },
    "BLTU": {
      "weight": 0.0272,
      "tier": "rare"
    },
    "RBGU": {
      "weight": 0.0248,
      "tier": "rare"
    },
    "NSHO": {
      "weight": 0.0226,
      "tier": "rare"
    },
    "LESA": {
      "weight": 0.0204,
      "tier": "rare"
    },
    "GWFG": {
      "weight": 0.0203,
      "tier": "rare"
    },
    "BHCO": {
      "weight": 0.0192,
      "tier": "rare"
    },
    "WATA": {
      "weight": 0.0181,
      "tier": "rare"
    },
    "CACG": {
      "weight": 0.0169,
      "tier": "rare"
    },
    "WHIM": {
      "weight": 0.0158,
      "tier": "rare"
    },
    "SURF": {
      "weight": 0.0136,
      "tier": "rare"
    },
    "AMWI": {
      "weight": 0.0124,
      "tier": "rare"
    },
    "WESA": {
      "weight": 0.0124,
      "tier": "rare"
    },
    "STAL": {
      "weight": 0.0113,
      "tier": "rare"
    },
    "GRSH": {
      "weight": 0.0113,
      "tier": "rare"
    },
    "SAND": {
      "weight": 0.0102,
      "tier": "rare"
    },
    "PEFA": {
      "weight": 0.0102,
      "tier": "rare"
    },
    "RNGR": {
      "weight": 0.009,
      "tier": "vagrant"
    },
    "MALL": {
      "weight": 0.0079,
      "tier": "vagrant"
    },
    "GLGU": {
      "weight": 0.0079,
      "tier": "vagrant"
    },
    "WISP": {
      "weight": 0.0079,
      "tier": "vagrant"
    },
    "YEWA": {
      "weight": 0.0079,
      "tier": "vagrant"
    },
    "TOWA": {
      "weight": 0.0079,
      "tier": "vagrant"
    },
    "GRSC": {
      "weight": 0.0068,
      "tier": "vagrant"
    },
    "OCWA": {
      "weight": 0.0068,
      "tier": "vagrant"
    },
    "WIWA": {
      "weight": 0.0057,
      "tier": "vagrant"
    },
    "BBPL": {
      "weight": 0.0056,
      "tier": "vagrant"
    },
    "HOPU": {
      "weight": 0.0056,
      "tier": "vagrant"
    },
    "DEJU": {
      "weight": 0.0056,
      "tier": "vagrant"
    },
    "YRWA": {
      "weight": 0.0056,
      "tier": "vagrant"
    },
    "COBO": {
      "weight": 0.0046,
      "tier": "vagrant"
    },
    "RUHU": {
      "weight": 0.0045,
      "tier": "vagrant"
    },
    "GUMU": {
      "weight": 0.0045,
      "tier": "vagrant"
    },
    "WEWV": {
      "weight": 0.0045,
      "tier": "vagrant"
    },
    "RCKI": {
      "weight": 0.0045,
      "tier": "vagrant"
    },
    "GCKI": {
      "weight": 0.0045,
      "tier": "vagrant"
    },
    "SAVS": {
      "weight": 0.0045,
      "tier": "vagrant"
    },
    "HADU": {
      "weight": 0.0034,
      "tier": "vagrant"
    },
    "ELTE": {
      "weight": 0.0034,
      "tier": "vagrant"
    },
    "HAPE": {
      "weight": 0.0034,
      "tier": "vagrant"
    },
    "BEKI": {
      "weight": 0.0034,
      "tier": "vagrant"
    },
    "PISI": {
      "weight": 0.0034,
      "tier": "vagrant"
    },
    "SEPL": {
      "weight": 0.0024,
      "tier": "vagrant"
    },
    "LESC": {
      "weight": 0.0023,
      "tier": "vagrant"
    },
    "LTDU": {
      "weight": 0.0023,
      "tier": "vagrant"
    },
    "SBDO": {
      "weight": 0.0023,
      "tier": "vagrant"
    },
    "DUNL": {
      "weight": 0.0023,
      "tier": "vagrant"
    },
    "RLKI": {
      "weight": 0.0023,
      "tier": "vagrant"
    },
    "FRGU": {
      "weight": 0.0023,
      "tier": "vagrant"
    },
    "MOPE": {
      "weight": 0.0023,
      "tier": "vagrant"
    },
    "GBHE": {
      "weight": 0.0023,
      "tier": "vagrant"
    },
    "NOFL": {
      "weight": 0.0023,
      "tier": "vagrant"
    },
    "CEDW": {
      "weight": 0.0023,
      "tier": "vagrant"
    },
    "AMPI": {
      "weight": 0.0023,
      "tier": "vagrant"
    },
    "WCSP": {
      "weight": 0.0023,
      "tier": "vagrant"
    },
    "RUTU": {
      "weight": 0.0012,
      "tier": "vagrant"
    },
    "MUPE": {
      "weight": 0.0012,
      "tier": "vagrant"
    },
    "RBME": {
      "weight": 0.0011,
      "tier": "vagrant"
    },
    "MAGO": {
      "weight": 0.0011,
      "tier": "vagrant"
    },
    "SPSA": {
      "weight": 0.0011,
      "tier": "vagrant"
    },
    "REKN": {
      "weight": 0.0011,
      "tier": "vagrant"
    },
    "BASA": {
      "weight": 0.0011,
      "tier": "vagrant"
    },
    "TBMU": {
      "weight": 0.0011,
      "tier": "vagrant"
    },
    "LIGU": {
      "weight": 0.0011,
      "tier": "vagrant"
    },
    "HOGR": {
      "weight": 0.0011,
      "tier": "vagrant"
    },
    "NABO": {
      "weight": 0.0011,
      "tier": "vagrant"
    },
    "SEOW": {
      "weight": 0.0011,
      "tier": "vagrant"
    },
    "MERL": {
      "weight": 0.0011,
      "tier": "vagrant"
    },
    "WEWP": {
      "weight": 0.0011,
      "tier": "vagrant"
    },
    "HOLA": {
      "weight": 0.0011,
      "tier": "vagrant"
    },
    "BARS": {
      "weight": 0.0011,
      "tier": "vagrant"
    },
    "CLSW": {
      "weight": 0.0011,
      "tier": "vagrant"
    },
    "VATH": {
      "weight": 0.0011,
      "tier": "vagrant"
    },
    "AMRO": {
      "weight": 0.0011,
      "tier": "vagrant"
    },
    "GRAW": {
      "weight": 0.0011,
      "tier": "vagrant"
    },
    "RECR": {
      "weight": 0.0011,
      "tier": "vagrant"
    },
    "AGOL": {
      "weight": 0.0011,
      "tier": "vagrant"
    },
    "LALO": {
      "weight": 0.0011,
      "tier": "vagrant"
    },
    "SOSP": {
      "weight": 0.0011,
      "tier": "vagrant"
    },
    "YHBL": {
      "weight": 0.0011,
      "tier": "vagrant"
    },
    "RWBL": {
      "weight": 0.0011,
      "tier": "vagrant"
    },
    "MGWA": {
      "weight": 0.0011,
      "tier": "vagrant"
    },
    "PAWA": {
      "weight": 0.0011,
      "tier": "vagrant"
    },
    "CONI": {
      "weight": 0.0001,
      "tier": "vagrant"
    },
    "CLGR": {
      "weight": 0.0001,
      "tier": "vagrant"
    },
    "BLSC": {
      "weight": 0.0,
      "tier": "vagrant"
    },
    "ROSA": {
      "weight": 0.0,
      "tier": "vagrant"
    },
    "YBLO": {
      "weight": 0.0,
      "tier": "vagrant"
    },
    "RBNU": {
      "weight": 0.0,
      "tier": "vagrant"
    },
    "ROWR": {
      "weight": 0.0,
      "tier": "vagrant"
    },
    "TOSO": {
      "weight": 0.0,
      "tier": "vagrant"
    }
  }
}